[
  {
    "id": 1,
    "function": "new",
    "file": "Chap12/Exercise12_1.rs",
    "lines": "32-33",
    "spec_strength": "hole",
    "snippet": "        fn new() -> (lock: Self)\n            ensures !lock.spec_locked();"
  },
  {
    "id": 2,
    "function": "lock",
    "file": "Chap12/Exercise12_1.rs",
    "lines": "38-39",
    "spec_strength": "hole",
    "snippet": "        fn lock(&self)\n            ensures self.spec_locked();"
  },
  {
    "id": 3,
    "function": "unlock",
    "file": "Chap12/Exercise12_1.rs",
    "lines": "44-46",
    "spec_strength": "hole",
    "snippet": "        fn unlock(&self)\n            requires self.spec_locked()\n            ensures !self.spec_locked();"
  },
  {
    "id": 4,
    "function": "with_lock",
    "file": "Chap12/Exercise12_1.rs",
    "lines": "53",
    "spec_strength": "hole",
    "snippet": "        fn with_lock<T, F: FnOnce() -> T>(&self, action: F) -> T;"
  },
  {
    "id": 5,
    "function": "parallel_increment",
    "file": "Chap12/Exercise12_1.rs",
    "lines": "93-94",
    "spec_strength": "hole",
    "snippet": "    pub fn parallel_increment(iterations: usize) -> (incremented: usize)\n        ensures incremented == 4 * iterations"
  },
  {
    "id": 6,
    "function": "default",
    "file": "Chap12/Exercise12_1.rs",
    "lines": "120",
    "spec_strength": "",
    "snippet": "    fn default() -> Self { SpinLock::new() }"
  },
  {
    "id": 7,
    "function": "fetch_add_cas",
    "file": "Chap12/Exercise12_2.rs",
    "lines": "22",
    "spec_strength": "",
    "snippet": "    fn fetch_add_cas(&self, delta: usize) -> (previous: usize);"
  },
  {
    "id": 8,
    "function": "new",
    "file": "Chap12/Exercise12_5.rs",
    "lines": "58-59",
    "spec_strength": "hole",
    "snippet": "    fn new() -> (stack: Self)\n        ensures stack.wf();"
  },
  {
    "id": 9,
    "function": "push",
    "file": "Chap12/Exercise12_5.rs",
    "lines": "64-65",
    "spec_strength": "hole",
    "snippet": "    fn push(&self, value: T)\n        requires self.wf();"
  },
  {
    "id": 10,
    "function": "pop",
    "file": "Chap12/Exercise12_5.rs",
    "lines": "72-73",
    "spec_strength": "hole",
    "snippet": "    fn pop(&self) -> (possible_top: Option<T>)\n        requires self.wf();"
  },
  {
    "id": 11,
    "function": "is_empty",
    "file": "Chap12/Exercise12_5.rs",
    "lines": "79-80",
    "spec_strength": "hole",
    "snippet": "    fn is_empty(&self) -> (empty: bool)\n        requires self.wf();"
  },
  {
    "id": 12,
    "function": "drain",
    "file": "Chap12/Exercise12_5.rs",
    "lines": "87-88",
    "spec_strength": "hole",
    "snippet": "    fn drain(&self) -> (items: Vec<T>)\n        requires self.wf();"
  },
  {
    "id": 13,
    "function": "default",
    "file": "Chap12/Exercise12_5.rs",
    "lines": "148",
    "spec_strength": "",
    "snippet": "    fn default() -> Self { "
  },
  {
    "id": 14,
    "function": "drop",
    "file": "Chap12/Exercise12_5.rs",
    "lines": "155-157",
    "spec_strength": "hole",
    "snippet": "    fn drop(&mut self)\n        opens_invariants none\n        no_unwind"
  }
]